nonsqlite
