Metadata-Version: 1.0
Name: nonsqlite
Version: 0.6.11
Summary: Non SQL Database
Home-page: https://github.com/emilianobilli/nonsqlite
Author: Emiliano Billi
Author-email: emiliano.billi@gmail.com
License: GPL
Platform: UNKNOWN
